{
  "country": "yemen",
  "last_updated": "2026-06-02T14:58:19Z",
  "categories": [
    "Diplomacy",
    "Military",
    "Energy",
    "Economy",
    "Local Events"
  ],
  "stories": {
    "Diplomacy": [
      {
        "_id": "f6b045af4099",
        "title": "Those who carry incense burners are the ones who make small sparks",
        "source": "Yemenat",
        "url": "https://yemenat.net/archives/424093",
        "published_date": "2026-06-01T23:55:22Z",
        "category": "Diplomacy"
      },
      {
        "_id": "140f935be5eb",
        "title": "The vision of the listening group: either a state of national partnership or imminent collapse",
        "source": "Yemenat",
        "url": "https://yemenat.net/archives/424090",
        "published_date": "2026-06-01T23:47:52Z",
        "category": "Diplomacy"
      },
      {
        "_id": "f44c39683ab5",
        "title": "Goodbye Anis Hassan Yahya: The departure of the voice of reason that did not calm down",
        "source": "Yemenat",
        "url": "https://yemenat.net/archives/424086",
        "published_date": "2026-06-01T21:36:46Z",
        "category": "Diplomacy"
      },
      {
        "_id": "9f448c80f485",
        "title": "Oh agreement.. Oh hypocrisy.. Oh separation",
        "source": "Yemenat",
        "url": "https://yemenat.net/archives/424079",
        "published_date": "2026-06-01T17:35:37Z",
        "category": "Diplomacy"
      },
      {
        "_id": "901854ce9706",
        "title": "Military reinforcements heading to the west coast",
        "source": "Yemenat",
        "url": "https://yemenat.net/archives/424042",
        "published_date": "2026-05-31T21:49:54Z",
        "category": "Diplomacy"
      },
      {
        "_id": "e2424488bff7",
        "title": "A Quietly Narrated Solitude in Khalid Al-Yousef’s (The Solitude of Daylight)",
        "source": "Yemenat",
        "url": "https://yemenat.net/archives/424040",
        "published_date": "2026-05-31T21:19:30Z",
        "category": "Diplomacy"
      },
      {
        "_id": "37e96f709c32",
        "title": "Free tweets... when I drank shattered glass",
        "source": "Yemenat",
        "url": "https://yemenat.net/archives/424023",
        "published_date": "2026-05-31T12:08:22Z",
        "category": "Diplomacy"
      },
      {
        "_id": "c0bf6675dbdd",
        "title": "Yemenia announces that it is forced to make adjustments to the pilgrims’ transportation program due to the fuel crisis",
        "source": "Yemenat",
        "url": "https://yemenat.net/archives/424019",
        "published_date": "2026-05-31T11:24:30Z",
        "category": "Diplomacy"
      },
      {
        "_id": "2008ab310f68",
        "title": "Civil society organizations submit an opinion request to the United Nations Legal Counsel regarding the constitutional status of Yemen after the death of President Hadi",
        "source": "Yemenat",
        "url": "https://yemenat.net/archives/424011",
        "published_date": "2026-05-31T09:37:06Z",
        "category": "Diplomacy"
      },
      {
        "_id": "a1d4d8a0d05a",
        "title": "The independence of Hashid is an unforgivable accusation. Do not assassinate the silence of pain",
        "source": "Yemenat",
        "url": "https://yemenat.net/archives/423971",
        "published_date": "2026-05-30T22:14:37Z",
        "category": "Diplomacy"
      },
      {
        "_id": "3fb10fb6d13f",
        "title": "Let the servant of his Lord sleep in peace... Republics are not judged by herd logic",
        "source": "Yemenat",
        "url": "https://yemenat.net/archives/423945",
        "published_date": "2026-05-30T15:55:42Z",
        "category": "Diplomacy"
      },
      {
        "_id": "de8fa1538719",
        "title": "A loneliness that is told quietly in “The Loneliness of the Day” by Khaled Al-Youssef",
        "source": "Yemenat",
        "url": "https://yemenat.net/archives/423938",
        "published_date": "2026-05-30T14:33:22Z",
        "category": "Diplomacy"
      },
      {
        "_id": "04faf754c30a",
        "title": "Trump announces the lifting of the naval blockade on Iran",
        "source": "Yemenat",
        "url": "https://yemenat.net/archives/423920",
        "published_date": "2026-05-29T19:10:23Z",
        "category": "Diplomacy"
      },
      {
        "_id": "3a2e8a583b8f",
        "title": "The funeral of former President Hadi in Riyadh",
        "source": "Yemenat",
        "url": "https://yemenat.net/archives/423909",
        "published_date": "2026-05-29T15:44:18Z",
        "category": "Diplomacy"
      }
    ],
    "Military": [
      {
        "_id": "3576b4f51d04",
        "title": "The Israeli army announces that 4 soldiers were injured in a drone explosion launched by Hezbollah",
        "source": "Yemenat",
        "url": "https://yemenat.net/archives/424053",
        "published_date": "2026-06-01T00:40:50Z",
        "category": "Military"
      }
    ],
    "Energy": [],
    "Economy": [
      {
        "_id": "d24bcd9ba9c6",
        "title": "Important notes about the Al-Qutaie’ Festival for Yemeni Tihami heritage and folklore",
        "source": "Yemenat",
        "url": "https://yemenat.net/archives/424076",
        "published_date": "2026-06-01T16:19:24Z",
        "category": "Economy"
      },
      {
        "_id": "9d23c5ff1dfa",
        "title": "Leukemia Suffering and Time",
        "source": "Yemenat",
        "url": "https://yemenat.net/archives/424051",
        "published_date": "2026-06-01T00:29:39Z",
        "category": "Economy"
      }
    ],
    "Local Events": [
      {
        "_id": "7005a93ea433",
        "title": "Aden.. Clashes between Somalis and Ethiopians, and the company intervenes to resolve the clash",
        "source": "Yemenat",
        "url": "https://yemenat.net/archives/424103",
        "published_date": "2026-06-02T12:55:30Z",
        "category": "Local Events"
      },
      {
        "_id": "02e36692caf9",
        "title": "History is not written by emergencies",
        "source": "Yemenat",
        "url": "https://yemenat.net/archives/424099",
        "published_date": "2026-06-02T10:41:12Z",
        "category": "Local Events"
      },
      {
        "_id": "cab258556087",
        "title": "Meteorology: Hot to very hot weather in deserts, plateaus and coasts, and thunderstorms in the highlands.",
        "source": "Yemenat",
        "url": "https://yemenat.net/archives/424097",
        "published_date": "2026-06-02T10:21:12Z",
        "category": "Local Events"
      },
      {
        "_id": "4a4d9c1c3189",
        "title": "Corruption in Yemen...turned the lives of Yemenis into hell",
        "source": "Yemenat",
        "url": "https://yemenat.net/archives/424095",
        "published_date": "2026-06-02T00:08:30Z",
        "category": "Local Events"
      },
      {
        "_id": "9a52f755ab0b",
        "title": "All solidarity with Sheikh Sultan Al Sami against the treason campaigns",
        "source": "Yemenat",
        "url": "https://yemenat.net/archives/424088",
        "published_date": "2026-06-01T22:10:07Z",
        "category": "Local Events"
      },
      {
        "_id": "5e7e91765036",
        "title": "Activists call for speedy detection of perpetrators who destroyed old grape trees in Amran “Details”",
        "source": "Yemenat",
        "url": "https://yemenat.net/archives/424082",
        "published_date": "2026-06-01T20:27:50Z",
        "category": "Local Events"
      },
      {
        "_id": "9044ea539a48",
        "title": "With branches of love and peace.. Sanaa and Taiz celebrate “Eid Al-Mashaker”",
        "source": "Yemenat",
        "url": "https://yemenat.net/archives/424067",
        "published_date": "2026-06-01T14:50:46Z",
        "category": "Local Events"
      },
      {
        "_id": "037a383e4afa",
        "title": "Unidentified persons vandalize a vineyard in Amran",
        "source": "Yemenat",
        "url": "https://yemenat.net/archives/424064",
        "published_date": "2026-06-01T14:19:42Z",
        "category": "Local Events"
      },
      {
        "_id": "61b1fb8a11e7",
        "title": "I apologize for my name",
        "source": "Yemenat",
        "url": "https://yemenat.net/archives/424061",
        "published_date": "2026-06-01T13:01:32Z",
        "category": "Local Events"
      },
      {
        "_id": "d8012d5c42ac",
        "title": "Meteorology: Thunderstorms of varying intensity continue in a number of governorates",
        "source": "Yemenat",
        "url": "https://yemenat.net/archives/424056",
        "published_date": "2026-06-01T11:24:07Z",
        "category": "Local Events"
      },
      {
        "_id": "7efdc3563663",
        "title": "The file of arrests and restrictions on movement is one of the most complex and painful humanitarian files",
        "source": "Yemenat",
        "url": "https://yemenat.net/archives/424049",
        "published_date": "2026-06-01T00:23:40Z",
        "category": "Local Events"
      },
      {
        "_id": "bbc4fdb14b37",
        "title": "When the honorable fighters leave one by one, the country remains more desolate",
        "source": "Yemenat",
        "url": "https://yemenat.net/archives/424047",
        "published_date": "2026-06-01T00:15:49Z",
        "category": "Local Events"
      },
      {
        "_id": "5c050f55dbdc",
        "title": "Little tricks",
        "source": "Yemenat",
        "url": "https://yemenat.net/archives/424038",
        "published_date": "2026-05-31T21:13:06Z",
        "category": "Local Events"
      },
      {
        "_id": "cf98aa7aadba",
        "title": "Taiz.. A boat hijacks a Yemeni fishing boat off the coast of Mokha",
        "source": "Yemenat",
        "url": "https://yemenat.net/archives/424036",
        "published_date": "2026-05-31T20:58:33Z",
        "category": "Local Events"
      },
      {
        "_id": "7833b3dd9bde",
        "title": "Two earthquakes were recorded from the Gulf of Aden",
        "source": "Yemenat",
        "url": "https://yemenat.net/archives/424031",
        "published_date": "2026-05-31T19:26:28Z",
        "category": "Local Events"
      },
      {
        "_id": "8282588f8053",
        "title": "The death of a senior leader in the Yemeni Socialist Party",
        "source": "Yemenat",
        "url": "https://yemenat.net/archives/424016",
        "published_date": "2026-05-31T10:52:28Z",
        "category": "Local Events"
      },
      {
        "_id": "ba010686b6b0",
        "title": "Meteorology: Hot weather in deserts and coasts, and thunderstorms in several governorates",
        "source": "Yemenat",
        "url": "https://yemenat.net/archives/424014",
        "published_date": "2026-05-31T10:13:36Z",
        "category": "Local Events"
      },
      {
        "_id": "8634d920a9a0",
        "title": "The accused opened fire from a height overlooking the point.. Updates: A young man was killed by a soldier’s bullets at a military point in Qubaita",
        "source": "Yemenat",
        "url": "https://yemenat.net/archives/423974",
        "published_date": "2026-05-30T23:20:15Z",
        "category": "Local Events"
      },
      {
        "_id": "b58a5eadc0e4",
        "title": "Three earthquakes were recorded from the Gulf of Aden and Hodeidah Governorate",
        "source": "Yemenat",
        "url": "https://yemenat.net/archives/423967",
        "published_date": "2026-05-30T21:32:05Z",
        "category": "Local Events"
      },
      {
        "_id": "8a8f82c9bf48",
        "title": "Intellectuals call on the Sanaa authority to release lawyer Abdul Majeed Sabra",
        "source": "Yemenat",
        "url": "https://yemenat.net/archives/423965",
        "published_date": "2026-05-30T20:30:19Z",
        "category": "Local Events"
      }
    ]
  }
}